{
  "config": {
    "pcaps": [
      {
        "device": 0,
        "pcap": "kvs-k10000-c100000000-zipf0.9-warmup",
        "warmup": true
      },
      {
        "device": 0,
        "pcap": "kvs-k10000-c100000000-zipf0.9",
        "warmup": false
      }
    ]
  },
  "counters": {
    "0": 1000000,
    "1": 1000000,
    "10": 0,
    "11": 0,
    "12": 0,
    "13": 0,
    "14": 0,
    "15": 0,
    "16": 0,
    "17": 0,
    "18": 0,
    "19": 0,
    "2": 1000000,
    "20": 0,
    "21": 0,
    "22": 0,
    "23": 0,
    "24": 0,
    "25": 0,
    "26": 0,
    "27": 0,
    "28": 0,
    "29": 966986,
    "3": 1000000,
    "30": 966986,
    "31": 670644,
    "32": 670644,
    "33": 670644,
    "34": 670644,
    "35": 670644,
    "36": 296342,
    "37": 296342,
    "38": 296342,
    "39": 296342,
    "4": 1000000,
    "40": 296342,
    "41": 296342,
    "42": 296342,
    "43": 33014,
    "44": 33014,
    "45": 33014,
    "46": 33014,
    "47": 0,
    "48": 0,
    "49": 0,
    "5": 1000000,
    "50": 0,
    "51": 0,
    "52": 0,
    "53": 0,
    "54": 0,
    "55": 0,
    "56": 0,
    "57": 33014,
    "58": 33014,
    "59": 33014,
    "6": 1000000,
    "60": 33014,
    "61": 33014,
    "62": 0,
    "63": 0,
    "64": 0,
    "65": 0,
    "66": 0,
    "67": 0,
    "68": 0,
    "69": 0,
    "7": 1000000,
    "70": 0,
    "71": 0,
    "72": 0,
    "73": 0,
    "74": 0,
    "75": 0,
    "76": 0,
    "77": 0,
    "8": 966986,
    "9": 0
  },
  "map_stats": [],
  "meta": {
    "avg_pkt_size": 188,
    "elapsed": 15999000,
    "total_bytes": 188000000,
    "total_packets": 1000000
  }
}